README
setup.cfg
setup.py
aodag/__init__.py
aodag.util.egg-info/PKG-INFO
aodag.util.egg-info/SOURCES.txt
aodag.util.egg-info/dependency_links.txt
aodag.util.egg-info/entry_points.txt
aodag.util.egg-info/not-zip-safe
aodag.util.egg-info/top_level.txt
aodag/util/__init__.py
aodag/util/mkpkg.py