Metadata-Version: 1.0
Name: aodag.util
Version: 0.0
Summary: command utilities for python developer
Home-page: UNKNOWN
Author: Atsushi Odagiri
Author-email: aodagx@gmail.com
License: BSD
Platform: UNKNOWN
Classifier: Development Status :: 3 - Alpha
Classifier: Programming Language :: Python
Classifier: Topic :: Software Development
Classifier: Topic :: Utilities
